nomnomdata/nominode/__init__.py
nomnomdata/nominode/cli.py
nomnomdata/nominode/samples/task_sample.yaml
nomnomdata/nominode/task.py
nomnomdata/nominode/util.py
nomnomdata_nominode-0.3.1.dist-info/entry_points.txt
nomnomdata_nominode-0.3.1.dist-info/COPYING.LESSER
nomnomdata_nominode-0.3.1.dist-info/COPYING
nomnomdata_nominode-0.3.1.dist-info/LICENSE
nomnomdata_nominode-0.3.1.dist-info/WHEEL
nomnomdata_nominode-0.3.1.dist-info/METADATA
nomnomdata_nominode-0.3.1.dist-info/RECORD
