Metadata-Version: 2.1
Name: nomnomdata-nominode
Version: 0.3.1
Summary: Package containing tooling for interacting with nominodes
Home-page: https://gitlab.com/nomnomdata/tools/nomnomdata-nominode
License: LGPL-3.0-only
Author: Nom Nom Data Inc
Author-email: info@nomnomdata.com
Requires-Python: >=3.7,<4.0
Classifier: License :: OSI Approved :: GNU Lesser General Public License v3 (LGPLv3)
Classifier: Programming Language :: Python :: 3
Classifier: Programming Language :: Python :: 3.7
Classifier: Programming Language :: Python :: 3.8
Classifier: Programming Language :: Python :: 3.9
Requires-Dist: dunamai (>=1.1.0,<2.0.0)
Requires-Dist: mergedeep (>=1.3.0,<2.0.0)
Requires-Dist: nomnomdata-auth (>=2.3.3,<3.0.0)
Requires-Dist: nomnomdata-cli (>=0.1.8,<0.2.0)
Requires-Dist: omegaconf (>=2.0.2,<3.0.0)
Requires-Dist: requests (>=2.24.0,<3.0.0)
Requires-Dist: typing (>=3.7.4,<4.0.0)
Project-URL: Repository, https://gitlab.com/nomnomdata/tools/nomnomdata-nominode
